odoo8_addon_purchase_payment-8.0.1.0.0-py2.7-nspkg.pth
odoo_addons/purchase_payment/__openerp__.py
odoo_addons/purchase_payment/__init__.py
odoo_addons/purchase_payment/README.rst
odoo_addons/purchase_payment/migrations/8.0.1.0.0/pre-migration.py
odoo8_addon_purchase_payment-8.0.1.0.0.dist-info/top_level.txt
odoo8_addon_purchase_payment-8.0.1.0.0.dist-info/WHEEL
odoo8_addon_purchase_payment-8.0.1.0.0.dist-info/RECORD
odoo8_addon_purchase_payment-8.0.1.0.0.dist-info/metadata.json
odoo8_addon_purchase_payment-8.0.1.0.0.dist-info/DESCRIPTION.rst
odoo8_addon_purchase_payment-8.0.1.0.0.dist-info/METADATA
odoo8_addon_purchase_payment-8.0.1.0.0.dist-info/namespace_packages.txt
